lskyup/__init__.py
lskyup/main.py
lskyup-0.1.5.dist-info/LICENSE
lskyup-0.1.5.dist-info/METADATA
lskyup-0.1.5.dist-info/WHEEL
lskyup-0.1.5.dist-info/entry_points.txt
lskyup-0.1.5.dist-info/top_level.txt
lskyup-0.1.5.dist-info/RECORD
