Metadata-Version: 2.1
Name: lskyup
Version: 0.1.5
Summary: A tool enables you to upload your img to your Lsky Server
Author: JoeZhu
Author-email: zhuzhouyue2005@outlook.com
License: GPLv3+
Classifier: Programming Language :: Python :: 3
Classifier: Operating System :: OS Independent
Requires-Python: >=3.6
License-File: LICENSE
Requires-Dist: setuptools (==67.7.2)
Requires-Dist: click (~=8.1.3)
Requires-Dist: requests (~=2.29.0)
Requires-Dist: Pillow (~=9.5.0)
